veris_memory_mcp_sdk-1.1.0.dist-info/licenses/LICENSE
veris_memory_sdk/__init__.py
veris_memory_sdk/core/__init__.py
veris_memory_sdk/core/client.py
veris_memory_sdk/core/config.py
veris_memory_sdk/core/errors.py
veris_memory_sdk/core/interfaces.py
veris_memory_sdk/core/logging_utils.py
veris_memory_sdk/core/resource_manager.py
veris_memory_sdk/core/schemas.py
veris_memory_sdk/core/security.py
veris_memory_sdk/core/tool_executor.py
veris_memory_sdk/core/validation.py
veris_memory_sdk/monitoring/__init__.py
veris_memory_sdk/monitoring/tracing.py
veris_memory_sdk/transport/__init__.py
veris_memory_sdk/transport/factory.py
veris_memory_sdk/transport/http_transport.py
veris_memory_sdk/transport/policies.py
veris_memory_sdk/transport/websocket_transport.py
veris_memory_mcp_sdk-1.1.0.dist-info/METADATA
veris_memory_mcp_sdk-1.1.0.dist-info/WHEEL
veris_memory_mcp_sdk-1.1.0.dist-info/top_level.txt
veris_memory_mcp_sdk-1.1.0.dist-info/RECORD
