Metadata-Version: 2.4
Name: veris-memory-mcp-sdk
Version: 1.1.0
Summary: Production-ready Python SDK for ◎ Veris Memory Model Context Protocol (MCP)
Home-page: https://github.com/credentum/veris-memory-mcp-sdk
Author: ◎ Veris Memory Team
Author-email: ◎ Veris Memory Team <credento@credentum.ai>
License: MIT
Project-URL: Documentation, https://credentum.ai/docs/sdk
Project-URL: Repository, https://github.com/credentum/veris-memory-mcp-sdk
Project-URL: Bug Tracker, https://github.com/credentum/veris-memory-mcp-sdk/issues
Project-URL: Changelog, https://github.com/credentum/veris-memory-mcp-sdk/blob/main/CHANGELOG.md
Keywords: mcp,model-context-protocol,veris-memory,context-management,ai
Classifier: Development Status :: 5 - Production/Stable
Classifier: Intended Audience :: Developers
Classifier: License :: OSI Approved :: MIT License
Classifier: Operating System :: OS Independent
Classifier: Programming Language :: Python :: 3
Classifier: Programming Language :: Python :: 3.10
Classifier: Programming Language :: Python :: 3.11
Classifier: Programming Language :: Python :: 3.12
Classifier: Topic :: Software Development :: Libraries :: Python Modules
Classifier: Topic :: Internet :: WWW/HTTP
Classifier: Topic :: System :: Networking
Classifier: Topic :: Scientific/Engineering :: Artificial Intelligence
Requires-Python: >=3.10
License-File: LICENSE
Requires-Dist: httpx>=0.24.0
Requires-Dist: websockets>=11.0.0
Requires-Dist: pydantic<3.0.0,>=1.10.0
Requires-Dist: typing-extensions>=4.0.0
Provides-Extra: dev
Requires-Dist: pytest>=7.0.0; extra == "dev"
Requires-Dist: pytest-asyncio>=0.21.0; extra == "dev"
Requires-Dist: pytest-cov>=4.0.0; extra == "dev"
Requires-Dist: black>=22.0.0; extra == "dev"
Requires-Dist: isort>=5.0.0; extra == "dev"
Requires-Dist: flake8>=5.0.0; extra == "dev"
Requires-Dist: mypy>=1.0.0; extra == "dev"
Requires-Dist: bandit>=1.7.0; extra == "dev"
Requires-Dist: coverage>=7.0.0; extra == "dev"
Requires-Dist: pre-commit>=2.20.0; extra == "dev"
Provides-Extra: monitoring
Requires-Dist: opentelemetry-api>=1.15.0; extra == "monitoring"
Requires-Dist: opentelemetry-sdk>=1.15.0; extra == "monitoring"
Requires-Dist: opentelemetry-exporter-jaeger>=1.15.0; extra == "monitoring"
Provides-Extra: all
Requires-Dist: pytest>=7.0.0; extra == "all"
Requires-Dist: pytest-asyncio>=0.21.0; extra == "all"
Requires-Dist: pytest-cov>=4.0.0; extra == "all"
Requires-Dist: black>=22.0.0; extra == "all"
Requires-Dist: isort>=5.0.0; extra == "all"
Requires-Dist: flake8>=5.0.0; extra == "all"
Requires-Dist: mypy>=1.0.0; extra == "all"
Requires-Dist: pre-commit>=2.20.0; extra == "all"
Requires-Dist: opentelemetry-api>=1.15.0; extra == "all"
Requires-Dist: opentelemetry-sdk>=1.15.0; extra == "all"
Requires-Dist: opentelemetry-exporter-jaeger>=1.15.0; extra == "all"
Dynamic: author
Dynamic: home-page
Dynamic: license-file
Dynamic: requires-python
